MANIFEST.in
setup.py
djangomi/__init__.py
djangomi/__init__.pyc
djangomi/init.py
djangomi/init.pyc
djangomi.egg-info/PKG-INFO
djangomi.egg-info/SOURCES.txt
djangomi.egg-info/dependency_links.txt
djangomi.egg-info/top_level.txt