Metadata-Version: 1.0
Name: djangomi
Version: 0.1
Summary: Django Mi(ni) for Django projects
Home-page: http://github.com/futurice/djangomi
Author: Jussi Vaihia
Author-email: jussi.vaihia@futurice.com
License: BSD
Keywords: django as flask
Platform: UNKNOWN
